locate_pixelcolor_cpp_parallelfor/README.md
locate_pixelcolor_cpp_parallelfor/__init__.py
locate_pixelcolor_cpp_parallelfor/cloop.dll
locate_pixelcolor_cpp_parallelfor/requirements.txt
locate_pixelcolor_cpp_parallelfor/thirdparty.json
locate_pixelcolor_cpp_parallelfor-0.11.dist-info/LICENSE.rst
locate_pixelcolor_cpp_parallelfor-0.11.dist-info/METADATA
locate_pixelcolor_cpp_parallelfor-0.11.dist-info/WHEEL
locate_pixelcolor_cpp_parallelfor-0.11.dist-info/top_level.txt
locate_pixelcolor_cpp_parallelfor-0.11.dist-info/RECORD
