Metadata-Version: 2.1
Name: locate-pixelcolor-cpp-parallelfor
Version: 0.11
Summary: Detects colors in images up to 10 x faster than Numpy
Home-page: https://github.com/hansalemaos/locate_pixelcolor_cpp_parallelfor
Author: Johannes Fischer
Author-email: aulasparticularesdealemaosp@gmail.com
License: MIT
Keywords: cpp,c++,image,search,parallel,rgb
Classifier: Development Status :: 4 - Beta
Classifier: Programming Language :: Python :: 3 :: Only
Classifier: Programming Language :: Python :: 3.10
Classifier: Topic :: Software Development :: Libraries :: Python Modules
Classifier: Topic :: Utilities
License-File: LICENSE.rst
Requires-Dist: numpy
